[
  {
    "forkortning": "AfS",
    "name": "alternativ-for-sverige",
    "partibeteckning": "Alternativ för Sverige",
    "uuid": "3f7caf00-f50b-4ce3-b135-04492de827b1",
    "valmyndigheten_id": "1325",
    "valmyndigheten_registreringsdatum": "2018-02-23"
  },
  {
    "forkortning": "S",
    "name": "arbetarepartiet-socialdemokraterna",
    "partibeteckning": "Arbetarepartiet-Socialdemokraterna",
    "uuid": "5e14c4c7-84c5-4770-ac14-d245902dd3cd",
    "valmyndigheten_id": "2",
    "valmyndigheten_registreringsdatum": "2017-11-02"
  },
  {
    "forkortning": "C",
    "name": "centerpartiet",
    "partibeteckning": "Centerpartiet",
    "uuid": "b9d4e933-3b5c-4780-9802-35e8dcf87ac3",
    "valmyndigheten_id": "4",
    "valmyndigheten_registreringsdatum": "2017-11-13"
  },
  {
    "forkortning": "DD",
    "name": "direktdemokraterna",
    "partibeteckning": "Direktdemokraterna",
    "uuid": "153c98fb-b712-4314-a922-9562253639c2",
    "valmyndigheten_id": "1150",
    "valmyndigheten_registreringsdatum": "2017-12-13"
  },
  {
    "forkortning": "DjuP",
    "name": "djurens-parti",
    "partibeteckning": "Djurens parti",
    "uuid": "e9f11067-9208-473c-9499-eed921f680a9",
    "valmyndigheten_id": "1136",
    "valmyndigheten_registreringsdatum": "2019-02-28"
  },
  {
    "forkortning": "ENH",
    "name": "enhet",
    "partibeteckning": "Enhet",
    "uuid": "4ed338ef-bbdd-4ff9-aaa9-b86c90a01e3e",
    "valmyndigheten_id": "189",
    "valmyndigheten_registreringsdatum": "2018-02-26"
  },
  {
    "forkortning": "EAP",
    "name": "europeiska-arbetarpartiet-eap",
    "partibeteckning": "Europeiska Arbetarpartiet-EAP",
    "uuid": "8c7f27e0-2da5-4594-89b7-b6d402e2b3aa",
    "valmyndigheten_id": "29",
    "valmyndigheten_registreringsdatum": "1985-03-22"
  },
  {
    "forkortning": "FI",
    "name": "feministiskt-initiativ",
    "partibeteckning": "Feministiskt initiativ",
    "uuid": "611c7fae-c057-4e46-8fd9-c4507c36be62",
    "valmyndigheten_id": "532",
    "valmyndigheten_registreringsdatum": "2017-11-02"
  },
  {
    "forkortning": "-",
    "name": "hogerpartiet-de-konservativa",
    "partibeteckning": "Högerpartiet de konservativa",
    "uuid": "94d45816-6e28-4736-becf-008e039e3bc0",
    "valmyndigheten_id": "452",
    "valmyndigheten_registreringsdatum": "2004-03-11"
  },
  {
    "forkortning": "INI",
    "name": "initiativet",
    "partibeteckning": "Initiativet",
    "uuid": "07b403b7-3b9b-4a22-844e-9f0fa516d57b",
    "valmyndigheten_id": "1374",
    "valmyndigheten_registreringsdatum": "2018-03-27"
  },
  {
    "forkortning": "KLP",
    "name": "klassiskt-liberala-partiet",
    "partibeteckning": "Klassiskt liberala partiet",
    "uuid": "6537fb90-7ac9-4385-b554-3074b9e60b1a",
    "valmyndigheten_id": "638",
    "valmyndigheten_registreringsdatum": "2017-12-18"
  },
  {
    "forkortning": "K",
    "name": "kommunistiska-partiet",
    "partibeteckning": "Kommunistiska Partiet",
    "uuid": "7d9b57e7-f172-4042-8a2e-ad18c5da6245",
    "valmyndigheten_id": "471",
    "valmyndigheten_registreringsdatum": "2018-03-16"
  },
  {
    "forkortning": "KD",
    "name": "kristdemokraterna",
    "partibeteckning": "Kristdemokraterna",
    "uuid": "d4ce485f-5e0e-4479-9d11-2147f337f20a",
    "valmyndigheten_id": "68",
    "valmyndigheten_registreringsdatum": "2017-11-02"
  },
  {
    "forkortning": "LPo",
    "name": "landsbygdspartiet-oberoende",
    "partibeteckning": "Landsbygdspartiet Oberoende",
    "uuid": "e39bddbe-ce7d-4c63-a677-b5c1a3046ebd",
    "valmyndigheten_id": "1011",
    "valmyndigheten_registreringsdatum": "2017-12-08"
  },
  {
    "forkortning": "L",
    "name": "liberalerna-tidigare-folkpartiet",
    "partibeteckning": "Liberalerna (tidigare Folkpartiet)",
    "uuid": "1a60396f-4551-4842-860e-7fcf1815dbe0",
    "valmyndigheten_id": "3",
    "valmyndigheten_registreringsdatum": "2017-11-13"
  },
  {
    "forkortning": "MED",
    "name": "medborgerlig-samling",
    "partibeteckning": "Medborgerlig Samling",
    "uuid": "68b3e558-d0bb-4ac7-b833-a5b30a542800",
    "valmyndigheten_id": "1296",
    "valmyndigheten_registreringsdatum": "2019-02-26"
  },
  {
    "forkortning": "MP",
    "name": "miljopartiet-de-grona",
    "partibeteckning": "Miljöpartiet de gröna",
    "uuid": "3de0287f-bf7c-45c4-97d9-9def4f24e133",
    "valmyndigheten_id": "55",
    "valmyndigheten_registreringsdatum": "2017-11-02"
  },
  {
    "forkortning": "M",
    "name": "moderaterna",
    "partibeteckning": "Moderaterna",
    "uuid": "ce96a63c-66d7-4b63-b5db-da7a0a579476",
    "valmyndigheten_id": "1",
    "valmyndigheten_registreringsdatum": "2017-11-13"
  },
  {
    "forkortning": "NMR",
    "name": "nordiska-motstandsrorelsen",
    "partibeteckning": "Nordiska motståndsrörelsen",
    "uuid": "c7ce3542-587c-4d95-8e2a-d63f91b11bc9",
    "valmyndigheten_id": "1273",
    "valmyndigheten_registreringsdatum": "2015-07-09"
  },
  {
    "forkortning": "PV",
    "name": "partiet-vandpunkt",
    "partibeteckning": "Partiet Vändpunkt",
    "uuid": "12e19db2-0113-4146-ae1f-c84d52016103",
    "valmyndigheten_id": "1430",
    "valmyndigheten_registreringsdatum": "2019-02-28"
  },
  {
    "forkortning": "PP",
    "name": "piratpartiet",
    "partibeteckning": "Piratpartiet",
    "uuid": "e6be8b6a-9385-4918-847a-dee620802595",
    "valmyndigheten_id": "524",
    "valmyndigheten_registreringsdatum": "2017-12-18"
  },
  {
    "forkortning": "RS",
    "name": "rattvisepartiet-socialisterna",
    "partibeteckning": "Rättvisepartiet Socialisterna",
    "uuid": "ce076c0a-bef8-401e-a65c-6882a0d384c0",
    "valmyndigheten_id": "131",
    "valmyndigheten_registreringsdatum": "2017-12-05"
  },
  {
    "forkortning": "SJP",
    "name": "sjobopartiet",
    "partibeteckning": "Sjöbopartiet",
    "uuid": "57a2224c-71dd-4d74-aae4-b53e097cdc20",
    "valmyndigheten_id": "172",
    "valmyndigheten_registreringsdatum": "1991-03-27"
  },
  {
    "forkortning": "SKÅ",
    "name": "skanepartiet",
    "partibeteckning": "SKÅNEPARTIET",
    "uuid": "96fa352b-a7d2-4bd0-bab9-37ab6c479d54",
    "valmyndigheten_id": "54",
    "valmyndigheten_registreringsdatum": "1979-05-15"
  },
  {
    "forkortning": "-",
    "name": "sociala-partiet-sp",
    "partibeteckning": "Sociala Partiet (SP)",
    "uuid": "640f040a-56c2-4b75-a240-733fa0eefd94",
    "valmyndigheten_id": "522",
    "valmyndigheten_registreringsdatum": "2009-02-11"
  },
  {
    "forkortning": "SOC.P",
    "name": "socialistiska-partiet",
    "partibeteckning": "Socialistiska Partiet",
    "uuid": "460d9564-c80d-4f42-a95a-518c956746c1",
    "valmyndigheten_id": "74",
    "valmyndigheten_registreringsdatum": "1985-02-18"
  },
  {
    "forkortning": "SPI",
    "name": "spi-valfarden",
    "partibeteckning": "SPI Välfärden",
    "uuid": "8a4715a7-04d9-4238-8edc-5f00300089f6",
    "valmyndigheten_id": "107",
    "valmyndigheten_registreringsdatum": "2013-07-02"
  },
  {
    "forkortning": "SD",
    "name": "sverigedemokraterna",
    "partibeteckning": "Sverigedemokraterna",
    "uuid": "b9af6417-6861-40ff-b0a5-3c1fab176496",
    "valmyndigheten_id": "110",
    "valmyndigheten_registreringsdatum": "2017-11-30"
  },
  {
    "forkortning": "TRP",
    "name": "trygghetspartiet",
    "partibeteckning": "TRYGGHETSPARTIET",
    "uuid": "c1b28696-4325-48c1-b40c-f8e530278dd0",
    "valmyndigheten_id": "1309",
    "valmyndigheten_registreringsdatum": "2017-10-20"
  },
  {
    "forkortning": "VägV",
    "name": "vagvalet",
    "partibeteckning": "Vägvalet",
    "uuid": "e35dbd0f-1df9-4dd5-97d8-8b82cdde0498",
    "valmyndigheten_id": "1138",
    "valmyndigheten_registreringsdatum": "2018-03-12"
  },
  {
    "forkortning": "V",
    "name": "vansterpartiet",
    "partibeteckning": "Vänsterpartiet",
    "uuid": "414d4a70-fcff-4390-9f70-5e259eb4fd0a",
    "valmyndigheten_id": "5",
    "valmyndigheten_registreringsdatum": "2017-11-02"
  },
  {
    "forkortning": "Kap",
    "name": "karlskronapartiet",
    "partibeteckning": "Karlskronapartiet",
    "uuid": "c96d2f6e-81ed-4a1c-89f5-a60058222f85",
    "valmyndigheten_id": "1139",
    "valmyndigheten_registreringsdatum": "2014-02-24"
  },
  {
    "forkortning": "SoL",
    "name": "sol-partiet-solvesborg-och-lister",
    "partibeteckning": "SoL-partiet Sölvesborg och Lister",
    "uuid": "0d562b39-da62-425d-bd18-869277f706b4",
    "valmyndigheten_id": "1257",
    "valmyndigheten_registreringsdatum": "2018-01-22"
  },
  {
    "forkortning": "dsp",
    "name": "dalarnas-sjukvardsparti",
    "partibeteckning": "Dalarnas Sjukvårdsparti",
    "uuid": "4d11b150-8aa4-44e4-ac99-7378407b67e4",
    "valmyndigheten_id": "472",
    "valmyndigheten_registreringsdatum": "2005-03-17"
  },
  {
    "forkortning": "MPPS",
    "name": "medborgarnas-politiska-parti-i-sverige",
    "partibeteckning": "Medborgarnas Politiska Parti i Sverige",
    "uuid": "245b9ede-33f6-4ae4-853c-898724a87900",
    "valmyndigheten_id": "1367",
    "valmyndigheten_registreringsdatum": "2018-03-29"
  },
  {
    "forkortning": "SJPG",
    "name": "sjukvardspartiet-gavleborg",
    "partibeteckning": "Sjukvårdspartiet Gävleborg",
    "uuid": "091e3961-b5f2-419b-8f6c-54fc7579e30c",
    "valmyndigheten_id": "249",
    "valmyndigheten_registreringsdatum": "2017-11-30"
  },
  {
    "forkortning": "Kbabo",
    "name": "kungsbackaborna",
    "partibeteckning": "Kungsbackaborna",
    "uuid": "4eee1cd3-a349-4c74-937c-3b7149b78d4e",
    "valmyndigheten_id": "1036",
    "valmyndigheten_registreringsdatum": "2017-12-05"
  },
  {
    "forkortning": "BA",
    "name": "bevara-akutsjukhusen",
    "partibeteckning": "Bevara akutsjukhusen",
    "uuid": "44273904-e60e-4323-885f-d7f4195e38d9",
    "valmyndigheten_id": "1355",
    "valmyndigheten_registreringsdatum": "2018-03-06"
  },
  {
    "forkortning": "EMP",
    "name": "empartiet",
    "partibeteckning": "EMPA(R)TIET",
    "uuid": "a8f1717a-818c-40d4-bfb3-f04dfd172e9f",
    "valmyndigheten_id": "1333",
    "valmyndigheten_registreringsdatum": "2018-01-29"
  },
  {
    "forkortning": "SJPJ",
    "name": "sjukvardspartiet-i-jonkopings-lan",
    "partibeteckning": "Sjukvårdspartiet i Jönköpings län",
    "uuid": "a57335f0-563a-42f5-98d0-8ccd1b11f140",
    "valmyndigheten_id": "1293",
    "valmyndigheten_registreringsdatum": "2017-03-09"
  },
  {
    "forkortning": "B-ALT",
    "name": "basta-alternativet",
    "partibeteckning": "Bästa Alternativet",
    "uuid": "b4c33957-dac8-4d56-b08a-19c877822487",
    "valmyndigheten_id": "1366",
    "valmyndigheten_registreringsdatum": "2018-03-29"
  },
  {
    "forkortning": "S-V",
    "name": "socialisterna-valfardspartiet",
    "partibeteckning": "Socialisterna-Välfärdspartiet",
    "uuid": "9897ef04-abc4-4226-b74b-016a2f9e56a0",
    "valmyndigheten_id": "977",
    "valmyndigheten_registreringsdatum": "2010-02-15"
  },
  {
    "forkortning": "RRP",
    "name": "rattvisa-rorelse-partiet",
    "partibeteckning": "Rättvisa Rörelse Partiet",
    "uuid": "59fbdd58-38df-4cb8-9800-628c91046ec9",
    "valmyndigheten_id": "1362",
    "valmyndigheten_registreringsdatum": "2018-04-09"
  },
  {
    "forkortning": "KNEG",
    "name": "knegarkampanjen",
    "partibeteckning": "Knegarkampanjen",
    "uuid": "b60ad164-adce-4c69-9438-074670153ab4",
    "valmyndigheten_id": "1168",
    "valmyndigheten_registreringsdatum": "2014-03-07"
  },
  {
    "forkortning": "SJV",
    "name": "sjukvardspartiet",
    "partibeteckning": "Sjukvårdspartiet",
    "uuid": "394593f1-a26f-4271-a0ff-e3e9c5df8b86",
    "valmyndigheten_id": "193",
    "valmyndigheten_registreringsdatum": "2017-05-23"
  },
  {
    "forkortning": "Alt",
    "name": "alternativet",
    "partibeteckning": "Alternativet",
    "uuid": "74cf42dc-1c73-4a54-8a20-71a71cce6723",
    "valmyndigheten_id": "1284",
    "valmyndigheten_registreringsdatum": "2017-11-02"
  },
  {
    "forkortning": "-",
    "name": "futurum-sverige",
    "partibeteckning": "Futurum Sverige",
    "uuid": "c4a3ff36-564b-46f6-81db-96ae77bfff77",
    "valmyndigheten_id": "1363",
    "valmyndigheten_registreringsdatum": "2018-03-21"
  },
  {
    "forkortning": "-",
    "name": "sveriges-nationella-demokratiska-parti",
    "partibeteckning": "Sveriges Nationella Demokratiska Parti",
    "uuid": "617f16c5-dd2f-4c10-a838-01c2b308c8a6",
    "valmyndigheten_id": "339",
    "valmyndigheten_registreringsdatum": "2002-04-09"
  },
  {
    "forkortning": "-",
    "name": "vardpartiet-i-skane",
    "partibeteckning": "Vårdpartiet i Skåne",
    "uuid": "f7e321ee-3b91-4471-915f-b876da4169f0",
    "valmyndigheten_id": "1119",
    "valmyndigheten_registreringsdatum": "2013-09-17"
  },
  {
    "forkortning": "-",
    "name": "lifepartiet",
    "partibeteckning": "Lifepartiet",
    "uuid": "22f28ecd-8bb9-4740-9a62-11c85d8fc061",
    "valmyndigheten_id": "1155",
    "valmyndigheten_registreringsdatum": "2014-03-07"
  },
  {
    "forkortning": "-",
    "name": "skoldkortelpartiet",
    "partibeteckning": "Sköldkörtelpartiet",
    "uuid": "4cdb24ff-2c49-4457-86c7-00661e381429",
    "valmyndigheten_id": "1359",
    "valmyndigheten_registreringsdatum": "2018-03-09"
  },
  {
    "forkortning": "-",
    "name": "stockholmspartiet",
    "partibeteckning": "Stockholmspartiet",
    "uuid": "1ad05d4a-8c99-472c-9205-5fb65344d4ed",
    "valmyndigheten_id": "555",
    "valmyndigheten_registreringsdatum": "2006-03-07"
  },
  {
    "forkortning": "VåfP",
    "name": "vard-for-pengarna",
    "partibeteckning": "Vård för Pengarna",
    "uuid": "4ef9af41-d2fa-475f-834b-4d722f3c8914",
    "valmyndigheten_id": "1122",
    "valmyndigheten_registreringsdatum": "2017-10-17"
  },
  {
    "forkortning": "USP",
    "name": "upplands-sjukvardsparti",
    "partibeteckning": "Upplands sjukvårdsparti",
    "uuid": "5d9c0cf0-f668-43a6-bbab-6dde4c91e56d",
    "valmyndigheten_id": "213",
    "valmyndigheten_registreringsdatum": "1999-11-24"
  },
  {
    "forkortning": "SjvV",
    "name": "sjukvardspartiet-i-varmland",
    "partibeteckning": "Sjukvårdspartiet i Värmland",
    "uuid": "d6511d4e-1b9d-4f3c-89ff-4533300f46fc",
    "valmyndigheten_id": "250",
    "valmyndigheten_registreringsdatum": "2017-12-05"
  },
  {
    "forkortning": "-",
    "name": "norrlandspartiet",
    "partibeteckning": "Norrlandspartiet",
    "uuid": "eaadd374-35f6-45da-acc4-4254289c77db",
    "valmyndigheten_id": "1298",
    "valmyndigheten_registreringsdatum": "2017-05-29"
  },
  {
    "forkortning": "-",
    "name": "norrlandska-valfardspartiet",
    "partibeteckning": "Norrländska Välfärdspartiet",
    "uuid": "1396159c-ac3b-48cd-82a2-b53e40e37a5c",
    "valmyndigheten_id": "1313",
    "valmyndigheten_registreringsdatum": "2017-11-30"
  },
  {
    "forkortning": "SJVP",
    "name": "sjukvardspartiet-vasternorrland",
    "partibeteckning": "Sjukvårdspartiet - Västernorrland",
    "uuid": "2dde7f18-4339-490a-abaf-43e4eb53205c",
    "valmyndigheten_id": "196",
    "valmyndigheten_registreringsdatum": "2017-12-22"
  },
  {
    "forkortning": "SjvU",
    "name": "sjukvardspartiet-vastmanland",
    "partibeteckning": "Sjukvårdspartiet - Västmanland",
    "uuid": "8d5a5e59-3c8d-43e8-a4c5-90957816cf12",
    "valmyndigheten_id": "500",
    "valmyndigheten_registreringsdatum": "2005-11-07"
  },
  {
    "forkortning": "DEM",
    "name": "demokraterna",
    "partibeteckning": "Demokraterna",
    "uuid": "45040bfa-87cf-44ec-aee8-f27724866aaf",
    "valmyndigheten_id": "1297",
    "valmyndigheten_registreringsdatum": "2018-03-16"
  },
  {
    "forkortning": "Vfp",
    "name": "medborgarpartiet",
    "partibeteckning": "Medborgarpartiet",
    "uuid": "ad2e4b90-40c6-4005-bcf5-766eaa101fa2",
    "valmyndigheten_id": "505",
    "valmyndigheten_registreringsdatum": "2017-08-14"
  },
  {
    "forkortning": "Rf",
    "name": "regionens-framtid",
    "partibeteckning": "Regionens framtid",
    "uuid": "0ea2696f-8b09-4eed-b02a-828239729b1a",
    "valmyndigheten_id": "1311",
    "valmyndigheten_registreringsdatum": "2018-02-26"
  },
  {
    "forkortning": "-",
    "name": "seniorpartiet",
    "partibeteckning": "Seniorpartiet",
    "uuid": "8ab621eb-f774-4428-a3d8-d8dbe713a448",
    "valmyndigheten_id": "470",
    "valmyndigheten_registreringsdatum": "2004-08-03"
  },
  {
    "forkortning": "SPVG",
    "name": "sjukvardspartiet-vastra-gotaland",
    "partibeteckning": "Sjukvårdspartiet - Västra Götaland",
    "uuid": "d4884d96-9160-4f1d-bb0f-b2a0efe7cbba",
    "valmyndigheten_id": "447",
    "valmyndigheten_registreringsdatum": "2018-01-03"
  },
  {
    "forkortning": "ÖrP",
    "name": "orebropartiet",
    "partibeteckning": "Örebropartiet",
    "uuid": "4719f829-c6f3-43b9-aaee-db26d645007d",
    "valmyndigheten_id": "1152",
    "valmyndigheten_registreringsdatum": "2014-03-07"
  },
  {
    "forkortning": "ADK",
    "name": "ale-demokraterna",
    "partibeteckning": "Ale - demokraterna",
    "uuid": "5b6ad59e-fa87-467b-b143-e35c13ad728b",
    "valmyndigheten_id": "139",
    "valmyndigheten_registreringsdatum": "2017-12-01"
  },
  {
    "forkortning": "FiA",
    "name": "framtid-i-ale",
    "partibeteckning": "FRAMTID I ALE",
    "uuid": "990c2123-0bc0-4534-8a36-a638109fc503",
    "valmyndigheten_id": "1158",
    "valmyndigheten_registreringsdatum": "2017-10-17"
  },
  {
    "forkortning": "ALV",
    "name": "alvesta-alternativet",
    "partibeteckning": "Alvesta Alternativet",
    "uuid": "c27c54ce-4d48-40aa-97a7-d7708f4c16df",
    "valmyndigheten_id": "124",
    "valmyndigheten_registreringsdatum": "1995-08-23"
  },
  {
    "forkortning": "OPA",
    "name": "omsorgspartiet-i-arboga",
    "partibeteckning": "Omsorgspartiet i Arboga",
    "uuid": "97e7e07e-7af2-4c39-8807-c7c18d60a5d1",
    "valmyndigheten_id": "335",
    "valmyndigheten_registreringsdatum": "2002-04-05"
  },
  {
    "forkortning": "AIL",
    "name": "kommunlistan",
    "partibeteckning": "Kommunlistan",
    "uuid": "61e71a07-8d03-4406-bab8-2819b6c2b80f",
    "valmyndigheten_id": "114",
    "valmyndigheten_registreringsdatum": "2014-01-16"
  },
  {
    "forkortning": "-",
    "name": "bjuvspartiet",
    "partibeteckning": "Bjuvspartiet",
    "uuid": "fb29cd49-782b-482a-b5d6-03671ee2abf8",
    "valmyndigheten_id": "1111",
    "valmyndigheten_registreringsdatum": "2014-11-04"
  },
  {
    "forkortning": "Bollp",
    "name": "bollnaspartiet",
    "partibeteckning": "Bollnäspartiet",
    "uuid": "30aab0fe-85ab-47b1-85b0-5511e0a5da4d",
    "valmyndigheten_id": "1013",
    "valmyndigheten_registreringsdatum": "2010-03-26"
  },
  {
    "forkortning": "FÖL",
    "name": "framtid-oland",
    "partibeteckning": "Framtid Öland",
    "uuid": "a6ed8e2b-6e19-4657-a083-ebe43a8d4a12",
    "valmyndigheten_id": "1142",
    "valmyndigheten_registreringsdatum": "2017-12-18"
  },
  {
    "forkortning": "Öland",
    "name": "olandspartiet",
    "partibeteckning": "Ölandspartiet",
    "uuid": "c79c8c7f-d06b-44f2-8749-de54938de492",
    "valmyndigheten_id": "336",
    "valmyndigheten_registreringsdatum": "2017-12-18"
  },
  {
    "forkortning": "Ofa",
    "name": "omsorg-for-alla",
    "partibeteckning": "Omsorg för alla",
    "uuid": "221f498a-d6cc-457b-bba7-f65f69a9f960",
    "valmyndigheten_id": "1369",
    "valmyndigheten_registreringsdatum": "2018-03-06"
  },
  {
    "forkortning": "Bov",
    "name": "borasvalet",
    "partibeteckning": "Boråsvalet",
    "uuid": "3f69dec1-6ce6-4341-ac6b-0de8a76546d4",
    "valmyndigheten_id": "1131",
    "valmyndigheten_registreringsdatum": "2014-01-24"
  },
  {
    "forkortning": "BP",
    "name": "botkyrkapartiet",
    "partibeteckning": "Botkyrkapartiet",
    "uuid": "85746d3e-59b5-4de5-bc1f-81aa2c3b655e",
    "valmyndigheten_id": "15",
    "valmyndigheten_registreringsdatum": "1988-02-10"
  },
  {
    "forkortning": "TuP",
    "name": "tullingepartiet",
    "partibeteckning": "Tullingepartiet",
    "uuid": "c0fec9af-ef73-43ec-9748-c82d98ab4514",
    "valmyndigheten_id": "711",
    "valmyndigheten_registreringsdatum": "2017-12-04"
  },
  {
    "forkortning": "BJP",
    "name": "bjarepartiet",
    "partibeteckning": "Bjärepartiet",
    "uuid": "45099053-dfc2-4b55-8eeb-8ab53b26f8a1",
    "valmyndigheten_id": "163",
    "valmyndigheten_registreringsdatum": "2017-12-05"
  },
  {
    "forkortning": "DKL",
    "name": "dorotea-kommunlista",
    "partibeteckning": "Dorotea Kommunlista",
    "uuid": "1d68b83f-c8bd-4d5f-907f-b8ae516a3a22",
    "valmyndigheten_id": "187",
    "valmyndigheten_registreringsdatum": "2017-12-22"
  },
  {
    "forkortning": "Ö",
    "name": "opartiet",
    "partibeteckning": "Öpartiet",
    "uuid": "10366f60-a96a-48f2-b248-5e3ece19e338",
    "valmyndigheten_id": "498",
    "valmyndigheten_registreringsdatum": "2018-01-29"
  },
  {
    "forkortning": "NE",
    "name": "nystart-enkoping-ne",
    "partibeteckning": "Nystart Enköping (NE)",
    "uuid": "f4f9b691-9eea-4cd7-906a-bbebb07a9c42",
    "valmyndigheten_id": "1143",
    "valmyndigheten_registreringsdatum": "2017-12-08"
  },
  {
    "forkortning": "NKE",
    "name": "nya-kommunpartiet-eslov",
    "partibeteckning": "Nya Kommunpartiet Eslöv",
    "uuid": "98e02aed-bbc7-410e-ae7e-77e2a9109fe7",
    "valmyndigheten_id": "988",
    "valmyndigheten_registreringsdatum": "2010-02-19"
  },
  {
    "forkortning": "FAP",
    "name": "falupartiet",
    "partibeteckning": "Falupartiet",
    "uuid": "07b1bc42-9681-47d6-89cd-59e0118a008a",
    "valmyndigheten_id": "201",
    "valmyndigheten_registreringsdatum": "1994-03-02"
  },
  {
    "forkortning": "Union",
    "name": "unionspartiet",
    "partibeteckning": "Unionspartiet",
    "uuid": "83dd748a-bd97-412c-87c7-51ae9b5fb196",
    "valmyndigheten_id": "1148",
    "valmyndigheten_registreringsdatum": "2014-03-28"
  },
  {
    "forkortning": "KOSA",
    "name": "kommunal-samling",
    "partibeteckning": "Kommunal Samling",
    "uuid": "0b9990ce-999d-4628-9634-d16188729059",
    "valmyndigheten_id": "1121",
    "valmyndigheten_registreringsdatum": "2013-10-01"
  },
  {
    "forkortning": "WeP",
    "name": "westbopartiet",
    "partibeteckning": "Westbopartiet",
    "uuid": "e19a05b1-3db0-4f2a-8389-2c2e4d482fe8",
    "valmyndigheten_id": "1335",
    "valmyndigheten_registreringsdatum": "2018-01-29"
  },
  {
    "forkortning": "MV",
    "name": "malmfaltens-val",
    "partibeteckning": "Malmfältens Väl",
    "uuid": "0487b4e2-d2a2-4ae9-9f92-e511d3687dab",
    "valmyndigheten_id": "509",
    "valmyndigheten_registreringsdatum": "2013-10-15"
  },
  {
    "forkortning": "-",
    "name": "asyl-nupartiet",
    "partibeteckning": "ASYL.NUPARTIET",
    "uuid": "ab4a2576-9338-4da7-98d0-dfeb324d4549",
    "valmyndigheten_id": "1352",
    "valmyndigheten_registreringsdatum": "2018-03-06"
  },
  {
    "forkortning": "-",
    "name": "barnpartiet",
    "partibeteckning": "Barnpartiet",
    "uuid": "f74e2503-2353-4442-a036-0c1894f55deb",
    "valmyndigheten_id": "1016",
    "valmyndigheten_registreringsdatum": "2010-03-04"
  },
  {
    "forkortning": "-",
    "name": "framtidspartiet-sverige",
    "partibeteckning": "Framtidspartiet Sverige",
    "uuid": "7f975e6b-1fa1-4d96-8c0d-6c7732306351",
    "valmyndigheten_id": "450",
    "valmyndigheten_registreringsdatum": "2004-01-30"
  },
  {
    "forkortning": "-",
    "name": "naturens-parti-sanning-rattvisa-karlek",
    "partibeteckning": "NATURENS PARTI SANNING RÄTTVISA KÄRLEK",
    "uuid": "e62f64e1-7b26-4a5e-93e7-637112a6e9ca",
    "valmyndigheten_id": "1281",
    "valmyndigheten_registreringsdatum": "2017-05-08"
  },
  {
    "forkortning": "-",
    "name": "normaldemokraterna",
    "partibeteckning": "Normaldemokraterna",
    "uuid": "7d941341-bac1-4610-a5c0-75e5f4d67f48",
    "valmyndigheten_id": "1124",
    "valmyndigheten_registreringsdatum": "2013-10-28"
  },
  {
    "forkortning": "-",
    "name": "oppna-goteborg-",
    "partibeteckning": "Öppna Göteborg!",
    "uuid": "04322f22-a4de-432a-9a68-be4845d2e4de",
    "valmyndigheten_id": "1130",
    "valmyndigheten_registreringsdatum": "2014-01-09"
  },
  {
    "forkortning": "GÖF",
    "name": "gotenes-framtid",
    "partibeteckning": "Götenes framtid",
    "uuid": "d60a251d-9a0c-4867-8971-444f9a006eb8",
    "valmyndigheten_id": "94",
    "valmyndigheten_registreringsdatum": "2018-02-08"
  },
  {
    "forkortning": "HaDem",
    "name": "habodemokraterna",
    "partibeteckning": "Habodemokraterna",
    "uuid": "3571a393-94b0-4aeb-b092-f3dabc9b6f5e",
    "valmyndigheten_id": "1287",
    "valmyndigheten_registreringsdatum": "2017-01-16"
  },
  {
    "forkortning": "OR",
    "name": "oberoende-realister",
    "partibeteckning": "OBEROENDE REALISTER",
    "uuid": "8463491f-4a86-4bfd-91d2-12d58ff5e223",
    "valmyndigheten_id": "1305",
    "valmyndigheten_registreringsdatum": "2017-11-02"
  },
  {
    "forkortning": "-",
    "name": "haningepartiet",
    "partibeteckning": "HANINGEPARTIET",
    "uuid": "c1338d92-1a30-45f2-8244-2c339eff16de",
    "valmyndigheten_id": "1272",
    "valmyndigheten_registreringsdatum": "2017-10-11"
  },
  {
    "forkortning": "L-P",
    "name": "det-lokala-partiet-i-heby-kommun",
    "partibeteckning": "DET LOKALA PARTIET I HEBY KOMMUN",
    "uuid": "6dd658b6-76ca-4da0-bb37-8ba2c39d60fe",
    "valmyndigheten_id": "103",
    "valmyndigheten_registreringsdatum": "2017-08-16"
  },
  {
    "forkortning": "KLH",
    "name": "kommunlistan",
    "partibeteckning": "Kommunlistan",
    "uuid": "1d9f94f2-18da-46bf-ab4f-d20cf2b95165",
    "valmyndigheten_id": "747",
    "valmyndigheten_registreringsdatum": "2015-04-20"
  },
  {
    "forkortning": "Ångf",
    "name": "angfarjepartiet",
    "partibeteckning": "Ångfärjepartiet",
    "uuid": "9d104e69-89ce-4090-bdad-8ae3435b8663",
    "valmyndigheten_id": "1162",
    "valmyndigheten_registreringsdatum": "2014-03-07"
  },
  {
    "forkortning": "KVäl",
    "name": "kommunens-val",
    "partibeteckning": "Kommunens Väl",
    "uuid": "500aa348-ede0-4d89-8b58-a08461cee764",
    "valmyndigheten_id": "526",
    "valmyndigheten_registreringsdatum": "2018-01-16"
  },
  {
    "forkortning": "DP",
    "name": "drevvikenpartiet",
    "partibeteckning": "Drevvikenpartiet",
    "uuid": "8ed0b238-a343-4e3b-b3a5-4cd430e9d7ff",
    "valmyndigheten_id": "122",
    "valmyndigheten_registreringsdatum": "2017-12-05"
  },
  {
    "forkortning": "HP",
    "name": "huddingepartiet",
    "partibeteckning": "Huddingepartiet",
    "uuid": "f056d271-b6d1-4b0b-98dc-f2c71f00138c",
    "valmyndigheten_id": "28",
    "valmyndigheten_registreringsdatum": "2018-03-12"
  },
  {
    "forkortning": "Komv",
    "name": "kommunens-val",
    "partibeteckning": "Kommunens Väl",
    "uuid": "9357c070-c6b0-4556-a790-a8c2c8db97eb",
    "valmyndigheten_id": "503",
    "valmyndigheten_registreringsdatum": "1979-04-19"
  },
  {
    "forkortning": "VOXH",
    "name": "folkets-rost-vox-humana",
    "partibeteckning": "Folkets röst - VOX humana",
    "uuid": "b1599806-fc9a-45bb-87e5-42de210597b0",
    "valmyndigheten_id": "119",
    "valmyndigheten_registreringsdatum": "1997-11-26"
  },
  {
    "forkortning": "Härjp",
    "name": "harjedalspartiet",
    "partibeteckning": "Härjedalspartiet",
    "uuid": "9f7fabe1-2a28-4fb9-88b8-de3cd17a8020",
    "valmyndigheten_id": "1106",
    "valmyndigheten_registreringsdatum": "2012-03-27"
  },
  {
    "forkortning": "KomP",
    "name": "kommunpartiet",
    "partibeteckning": "Kommunpartiet",
    "uuid": "8411e120-1d68-4435-bc7c-0f529b6d642a",
    "valmyndigheten_id": "546",
    "valmyndigheten_registreringsdatum": "2018-04-10"
  },
  {
    "forkortning": "SPP",
    "name": "sportpartiet",
    "partibeteckning": "Sportpartiet",
    "uuid": "035eb206-2fa5-4ba4-8226-33e08a5d425d",
    "valmyndigheten_id": "998",
    "valmyndigheten_registreringsdatum": "2010-02-26"
  },
  {
    "forkortning": "FOV",
    "name": "folkets-val",
    "partibeteckning": "Folkets Väl",
    "uuid": "81c13f0b-134f-4337-95ad-9539165e9dbf",
    "valmyndigheten_id": "126",
    "valmyndigheten_registreringsdatum": "2017-12-18"
  },
  {
    "forkortning": "-",
    "name": "kommunens-rost",
    "partibeteckning": "Kommunens Röst",
    "uuid": "44a507e9-3733-41ec-8eb7-dbad2c7c84be",
    "valmyndigheten_id": "1302",
    "valmyndigheten_registreringsdatum": "2017-06-22"
  },
  {
    "forkortning": "MedP",
    "name": "medborgarpartiet",
    "partibeteckning": "Medborgarpartiet",
    "uuid": "dc646f81-a2b4-44d3-8d5f-1e1802de6601",
    "valmyndigheten_id": "1299",
    "valmyndigheten_registreringsdatum": "2017-08-23"
  },
  {
    "forkortning": "FJK",
    "name": "framtid-i-jokkmokks-kommun",
    "partibeteckning": "Framtid i Jokkmokks kommun",
    "uuid": "6a91678c-924b-45f6-a281-26a363dcbbd8",
    "valmyndigheten_id": "1014",
    "valmyndigheten_registreringsdatum": "2010-03-04"
  },
  {
    "forkortning": "SV",
    "name": "samernas-val",
    "partibeteckning": "Samernas Väl",
    "uuid": "b77b63e0-84fa-4a87-97bb-8d72146ae208",
    "valmyndigheten_id": "80",
    "valmyndigheten_registreringsdatum": "2006-03-07"
  },
  {
    "forkortning": "KoDe",
    "name": "kommundemokraterna",
    "partibeteckning": "Kommundemokraterna",
    "uuid": "e782cd26-8d46-482f-b4f1-2b688fc9105b",
    "valmyndigheten_id": "1338",
    "valmyndigheten_registreringsdatum": "2018-02-08"
  },
  {
    "forkortning": "KXP",
    "name": "kalixpartiet",
    "partibeteckning": "Kalixpartiet",
    "uuid": "a2607113-2daa-4c79-8166-3d6e49b71423",
    "valmyndigheten_id": "141",
    "valmyndigheten_registreringsdatum": "1997-09-17"
  },
  {
    "forkortning": "KDL",
    "name": "karlstadpartiet-livskvalitet",
    "partibeteckning": "Karlstadpartiet Livskvalitet",
    "uuid": "d28154f7-af47-4248-9363-d38fd26aef61",
    "valmyndigheten_id": "1350",
    "valmyndigheten_registreringsdatum": "2018-03-27"
  },
  {
    "forkortning": "NKP",
    "name": "nya-kirunapartiet",
    "partibeteckning": "Nya Kirunapartiet",
    "uuid": "6639e412-737a-4308-992f-76b4f021910e",
    "valmyndigheten_id": "1326",
    "valmyndigheten_registreringsdatum": "2017-12-18"
  },
  {
    "forkortning": "VFK",
    "name": "var-framtid-klippan",
    "partibeteckning": "VÅR FRAMTID - KLIPPAN",
    "uuid": "635ee374-fdd4-4bfd-afaa-83668895fcd5",
    "valmyndigheten_id": "1393",
    "valmyndigheten_registreringsdatum": "2019-10-04"
  },
  {
    "forkortning": "KNU",
    "name": "knivsta-nu",
    "partibeteckning": "Knivsta.Nu",
    "uuid": "2cdb7e51-30e9-479b-b7f7-2d33cf915b73",
    "valmyndigheten_id": "303",
    "valmyndigheten_registreringsdatum": "2018-01-29"
  },
  {
    "forkortning": "KF",
    "name": "kristianstadsbygdens-framtid",
    "partibeteckning": "Kristianstadsbygdens Framtid",
    "uuid": "6ab877ef-e77c-4236-bbcf-f3b511fb29b1",
    "valmyndigheten_id": "442",
    "valmyndigheten_registreringsdatum": "2003-05-14"
  },
  {
    "forkortning": "ÅHP",
    "name": "ahuspartiet",
    "partibeteckning": "Åhuspartiet",
    "uuid": "ec774af6-5b29-4068-beb5-10d07e62a062",
    "valmyndigheten_id": "205",
    "valmyndigheten_registreringsdatum": "2017-12-18"
  },
  {
    "forkortning": "JVK",
    "name": "jamtlands-val-krokom",
    "partibeteckning": "Jämtlands Väl Krokom",
    "uuid": "511fcae2-33c6-4280-807f-2cfb3dae576a",
    "valmyndigheten_id": "1312",
    "valmyndigheten_registreringsdatum": "2017-12-22"
  },
  {
    "forkortning": "UtvP",
    "name": "utvecklingspartiet",
    "partibeteckning": "Utvecklingspartiet",
    "uuid": "cefdf9df-76d1-450c-8f74-f52523758486",
    "valmyndigheten_id": "978",
    "valmyndigheten_registreringsdatum": "2018-01-15"
  },
  {
    "forkortning": "Lap",
    "name": "laholmspartiet",
    "partibeteckning": "Laholmspartiet",
    "uuid": "05ac49a3-fa54-4d3a-8938-f947b380987f",
    "valmyndigheten_id": "418",
    "valmyndigheten_registreringsdatum": "2017-12-22"
  },
  {
    "forkortning": "FL",
    "name": "framtidspartiet-i-lekeberg",
    "partibeteckning": "Framtidspartiet i Lekeberg",
    "uuid": "4cf12d91-1c02-4fb0-86ce-8c7cd122ba50",
    "valmyndigheten_id": "997",
    "valmyndigheten_registreringsdatum": "2010-02-26"
  },
  {
    "forkortning": "ByP",
    "name": "bygdepartiet",
    "partibeteckning": "Bygdepartiet",
    "uuid": "b578db7a-cd4b-4e6c-826e-d53a0e142069",
    "valmyndigheten_id": "1053",
    "valmyndigheten_registreringsdatum": "2017-12-18"
  },
  {
    "forkortning": "LP",
    "name": "lidingopartiet",
    "partibeteckning": "Lidingöpartiet",
    "uuid": "14af0084-697b-4fec-b085-df63f90c9465",
    "valmyndigheten_id": "19",
    "valmyndigheten_registreringsdatum": "2018-04-10"
  },
  {
    "forkortning": "-",
    "name": "bjorn",
    "partibeteckning": "Bjorn",
    "uuid": "78a46d0f-68f7-4cea-bb32-4c89951db82e",
    "valmyndigheten_id": "474",
    "valmyndigheten_registreringsdatum": "2005-05-16"
  },
  {
    "forkortning": "-",
    "name": "folkfronten",
    "partibeteckning": "Folkfronten",
    "uuid": "16b66321-7512-4c21-b0e6-8b9815721781",
    "valmyndigheten_id": "828",
    "valmyndigheten_registreringsdatum": "2009-03-23"
  },
  {
    "forkortning": "KB",
    "name": "kommunens-basta-partipolitiskt-obunden-lista",
    "partibeteckning": "Kommunens Bästa (partipolitiskt obunden lista)",
    "uuid": "093e978b-c8cb-4383-a002-49a4ea34778d",
    "valmyndigheten_id": "521",
    "valmyndigheten_registreringsdatum": "2006-03-07"
  },
  {
    "forkortning": "DemRä",
    "name": "demokratisk-rattvisa",
    "partibeteckning": "Demokratisk Rättvisa",
    "uuid": "98d8ea70-a5bf-4cf7-8aff-18c9f38f6f60",
    "valmyndigheten_id": "1331",
    "valmyndigheten_registreringsdatum": "2018-01-11"
  },
  {
    "forkortning": "LjP",
    "name": "ljusdalsbygdens-parti",
    "partibeteckning": "Ljusdalsbygdens parti",
    "uuid": "62970bde-1b67-469b-954a-33078773b42b",
    "valmyndigheten_id": "535",
    "valmyndigheten_registreringsdatum": "2017-10-17"
  },
  {
    "forkortning": "FBj",
    "name": "fokus-bjarred",
    "partibeteckning": "Fokus Bjärred",
    "uuid": "082c3b14-65fb-499d-a8b7-37c29eaa55e0",
    "valmyndigheten_id": "1344",
    "valmyndigheten_registreringsdatum": "2018-03-12"
  },
  {
    "forkortning": "BOP",
    "name": "bopartiet",
    "partibeteckning": "Bopartiet",
    "uuid": "2915db45-e9a7-4cd4-9f93-d3f5ebf42bbe",
    "valmyndigheten_id": "117",
    "valmyndigheten_registreringsdatum": "1986-05-06"
  },
  {
    "forkortning": "FöNyL",
    "name": "fornyalund",
    "partibeteckning": "FörNyaLund",
    "uuid": "083558f5-89f8-4513-9ed1-6e5d309ec24a",
    "valmyndigheten_id": "1135",
    "valmyndigheten_registreringsdatum": "2018-03-26"
  },
  {
    "forkortning": "RoPa",
    "name": "romelepartiet-skane",
    "partibeteckning": "Romelepartiet Skåne",
    "uuid": "d11853ce-4206-4b7a-a222-2d107200dca1",
    "valmyndigheten_id": "1339",
    "valmyndigheten_registreringsdatum": "2018-02-16"
  },
  {
    "forkortning": "LP.NU",
    "name": "lysekilspartiet",
    "partibeteckning": "Lysekilspartiet",
    "uuid": "5b6a8475-6d85-466e-a34f-008852c173f7",
    "valmyndigheten_id": "248",
    "valmyndigheten_registreringsdatum": "2014-01-16"
  },
  {
    "forkortning": "-",
    "name": "gula-partiet",
    "partibeteckning": "Gula Partiet",
    "uuid": "821df78a-261b-4612-8e95-f3d10b3acd2a",
    "valmyndigheten_id": "1108",
    "valmyndigheten_registreringsdatum": "2012-09-11"
  },
  {
    "forkortning": "Komm.",
    "name": "kommunisterna",
    "partibeteckning": "Kommunisterna",
    "uuid": "55cdd0ac-6e10-42df-adf7-02db7dea7607",
    "valmyndigheten_id": "672",
    "valmyndigheten_registreringsdatum": "2010-03-12"
  },
  {
    "forkortning": "-",
    "name": "nks-nya-koalitionssamlingen",
    "partibeteckning": "NKS Nya Koalitionssamlingen",
    "uuid": "89ad9bef-dc40-4bd3-a70e-441ab8ee4103",
    "valmyndigheten_id": "1340",
    "valmyndigheten_registreringsdatum": "2018-03-13"
  },
  {
    "forkortning": "-",
    "name": "riksdemokraterna-for-sverige",
    "partibeteckning": "Riksdemokraterna för Sverige",
    "uuid": "6613a0a3-015b-4dfa-bfe3-9d0bf77f82b4",
    "valmyndigheten_id": "1279",
    "valmyndigheten_registreringsdatum": "2015-05-07"
  },
  {
    "forkortning": "ML",
    "name": "malalistan",
    "partibeteckning": "Malålistan",
    "uuid": "94de475b-521e-4fd6-b5e2-16eeacde72b4",
    "valmyndigheten_id": "525",
    "valmyndigheten_registreringsdatum": "2006-02-23"
  },
  {
    "forkortning": "MaP",
    "name": "mariestadspartiet",
    "partibeteckning": "MariestadsPartiet",
    "uuid": "8d8034b7-d41c-404b-8895-42e5d752bebc",
    "valmyndigheten_id": "331",
    "valmyndigheten_registreringsdatum": "2002-03-13"
  },
  {
    "forkortning": "MOD",
    "name": "marks-oberoende-demokrater--mod",
    "partibeteckning": "Marks Oberoende Demokrater, MOD",
    "uuid": "18bc4293-c7ac-4245-b5a2-8d041a9b3112",
    "valmyndigheten_id": "722",
    "valmyndigheten_registreringsdatum": "2008-01-15"
  },
  {
    "forkortning": "KiM",
    "name": "kommunpartiet-mellerud",
    "partibeteckning": "KommunPartiet Mellerud",
    "uuid": "f2803c86-56ec-4d6f-bb99-6e847357b5f8",
    "valmyndigheten_id": "593",
    "valmyndigheten_registreringsdatum": "2017-12-08"
  },
  {
    "forkortning": "MOP",
    "name": "morapartiet",
    "partibeteckning": "Morapartiet",
    "uuid": "3c442003-5859-4ff9-a322-86898ba54e13",
    "valmyndigheten_id": "197",
    "valmyndigheten_registreringsdatum": "1994-03-22"
  },
  {
    "forkortning": "Ölp",
    "name": "olandspartiet-sodra",
    "partibeteckning": "Ölandspartiet södra",
    "uuid": "40214df8-8f99-464f-8cdf-d803e7167f60",
    "valmyndigheten_id": "554",
    "valmyndigheten_registreringsdatum": "2014-02-25"
  },
  {
    "forkortning": "NL",
    "name": "nackalistan",
    "partibeteckning": "Nackalistan",
    "uuid": "eeb297f7-5159-48b2-b6c0-ab92ebc9fa28",
    "valmyndigheten_id": "543",
    "valmyndigheten_registreringsdatum": "2018-01-15"
  },
  {
    "forkortning": "NOR",
    "name": "norapartiet",
    "partibeteckning": "Norapartiet",
    "uuid": "1d7a2ecf-cd6c-478d-b6c6-95ff6e97c359",
    "valmyndigheten_id": "985",
    "valmyndigheten_registreringsdatum": "2017-12-08"
  },
  {
    "forkortning": "DiN",
    "name": "demokraterna-i-norberg",
    "partibeteckning": "Demokraterna i Norberg",
    "uuid": "42e96322-fb95-4088-a804-96c881a44d36",
    "valmyndigheten_id": "1304",
    "valmyndigheten_registreringsdatum": "2017-08-31"
  },
  {
    "forkortning": "PNF",
    "name": "partiet-for-norbergs-framtid",
    "partibeteckning": "Partiet för Norbergs Framtid",
    "uuid": "144fe5cd-0d20-4b11-bd0e-24fa1c9d4438",
    "valmyndigheten_id": "1137",
    "valmyndigheten_registreringsdatum": "2014-02-21"
  },
  {
    "forkortning": "nop",
    "name": "nordanstigspartiet-se",
    "partibeteckning": "nordanstigspartiet.se",
    "uuid": "38456bd0-8569-4c27-a4b5-fec604e0f381",
    "valmyndigheten_id": "1343",
    "valmyndigheten_registreringsdatum": "2018-02-16"
  },
  {
    "forkortning": "FD",
    "name": "fria-demokraterna",
    "partibeteckning": "Fria Demokraterna",
    "uuid": "da251d4e-1f74-42de-b440-91cac1078bc1",
    "valmyndigheten_id": "1280",
    "valmyndigheten_registreringsdatum": "2017-10-20"
  },
  {
    "forkortning": "ROOP",
    "name": "roslagens-oberoende-parti",
    "partibeteckning": "Roslagens oberoende parti",
    "uuid": "34fddde3-58bd-4390-8239-6b822fa7e313",
    "valmyndigheten_id": "1128",
    "valmyndigheten_registreringsdatum": "2018-01-22"
  },
  {
    "forkortning": "NP",
    "name": "nykvarnspartiet",
    "partibeteckning": "Nykvarnspartiet",
    "uuid": "d8c7d408-37c1-439c-a48d-805e00b4af49",
    "valmyndigheten_id": "123",
    "valmyndigheten_registreringsdatum": "2017-12-18"
  },
  {
    "forkortning": "PP(N)",
    "name": "pensionarspartiet-i-nynashamns-kommun",
    "partibeteckning": "Pensionärspartiet i Nynäshamns kommun",
    "uuid": "ac2f677a-f96e-41fd-869e-0a7ab2c24745",
    "valmyndigheten_id": "527",
    "valmyndigheten_registreringsdatum": "2014-02-25"
  },
  {
    "forkortning": "SN",
    "name": "sorundanet-nynashamns-kommunparti",
    "partibeteckning": "Sorundanet Nynäshamns kommunparti",
    "uuid": "51ed83cb-d87b-48e8-b6b2-f5a8f0491624",
    "valmyndigheten_id": "519",
    "valmyndigheten_registreringsdatum": "2017-12-08"
  },
  {
    "forkortning": "SAFE",
    "name": "solidaritet--arbete--fred--ekologi--safe",
    "partibeteckning": "Solidaritet, Arbete, Fred, Ekologi, SAFE",
    "uuid": "2c038150-7436-41b5-975e-c745ecbebc14",
    "valmyndigheten_id": "174",
    "valmyndigheten_registreringsdatum": "1991-03-05"
  },
  {
    "forkortning": "FPO",
    "name": "folkviljan-orust",
    "partibeteckning": "Folkviljan Orust",
    "uuid": "cc243f56-5c5a-4bd2-b649-0f685d0f7384",
    "valmyndigheten_id": "204",
    "valmyndigheten_registreringsdatum": "2018-01-03"
  },
  {
    "forkortning": "(OP)",
    "name": "orustpartiet-op",
    "partibeteckning": "Orustpartiet (OP)",
    "uuid": "2f00d90b-2195-4bb4-9575-4324dfabb7f2",
    "valmyndigheten_id": "1104",
    "valmyndigheten_registreringsdatum": "2011-12-21"
  },
  {
    "forkortning": "FrS",
    "name": "framtid-s",
    "partibeteckning": "Framtid S",
    "uuid": "655f6918-3cd2-40a5-819a-05ba458c1209",
    "valmyndigheten_id": "1361",
    "valmyndigheten_registreringsdatum": "2018-03-06"
  },
  {
    "forkortning": "PF",
    "name": "perstorps-framtid",
    "partibeteckning": "Perstorps Framtid",
    "uuid": "1eee2b77-0a39-4eb9-8b98-43b9628875a9",
    "valmyndigheten_id": "971",
    "valmyndigheten_registreringsdatum": "2009-11-04"
  },
  {
    "forkortning": "SkolP",
    "name": "skol-och-landsbygdspartiet",
    "partibeteckning": "Skol och Landsbygdspartiet",
    "uuid": "73d0ba2b-b024-4515-ad75-fbab558fb9ee",
    "valmyndigheten_id": "1216",
    "valmyndigheten_registreringsdatum": "2017-12-18"
  },
  {
    "forkortning": "AfR",
    "name": "allt-for-ragunda",
    "partibeteckning": "Allt för Ragunda",
    "uuid": "d62d3e66-de61-4897-a3d9-5511cd9c529b",
    "valmyndigheten_id": "497",
    "valmyndigheten_registreringsdatum": "2015-05-06"
  },
  {
    "forkortning": "ROP",
    "name": "ronnebypartiet",
    "partibeteckning": "Ronnebypartiet",
    "uuid": "66187f91-2cc5-4f83-b976-87ac13346da2",
    "valmyndigheten_id": "183",
    "valmyndigheten_registreringsdatum": "2010-03-04"
  },
  {
    "forkortning": "ViV",
    "name": "vi-i-verkligheten-ronneby-viv",
    "partibeteckning": "Vi i Verkligheten Ronneby (ViV)",
    "uuid": "321e4b97-efee-4982-9a14-3a1514b2009f",
    "valmyndigheten_id": "1341",
    "valmyndigheten_registreringsdatum": "2018-02-08"
  },
  {
    "forkortning": "SBÄ",
    "name": "salas-basta",
    "partibeteckning": "Salas bästa",
    "uuid": "121acbe1-ec5f-4964-bd94-6f4c94a52302",
    "valmyndigheten_id": "973",
    "valmyndigheten_registreringsdatum": "2009-12-18"
  },
  {
    "forkortning": "R",
    "name": "ronningepartiet",
    "partibeteckning": "Rönningepartiet",
    "uuid": "a653fd03-0c6a-41a3-8260-24a5ca4f441c",
    "valmyndigheten_id": "1080",
    "valmyndigheten_registreringsdatum": "2018-01-03"
  },
  {
    "forkortning": "SFS",
    "name": "sigtunapartiet-samling-for-sigtuna",
    "partibeteckning": "Sigtunapartiet Samling för Sigtuna",
    "uuid": "18b7efcb-527c-4886-8b8a-9ae9d68de88f",
    "valmyndigheten_id": "9",
    "valmyndigheten_registreringsdatum": "1999-04-06"
  },
  {
    "forkortning": "-",
    "name": "partiet-horisont",
    "partibeteckning": "Partiet Horisont",
    "uuid": "a53d194a-f771-44b3-b9a4-2f9c22ecb230",
    "valmyndigheten_id": "1368",
    "valmyndigheten_registreringsdatum": "2018-03-06"
  },
  {
    "forkortning": "ÖstP",
    "name": "osterlenpartiet",
    "partibeteckning": "Österlenpartiet",
    "uuid": "6675260d-0e34-4c06-842e-98312374dc21",
    "valmyndigheten_id": "422",
    "valmyndigheten_registreringsdatum": "2002-08-13"
  },
  {
    "forkortning": "SF",
    "name": "svenska-folkhemspartiet",
    "partibeteckning": "Svenska Folkhemspartiet",
    "uuid": "dc43e9e9-957d-4851-900b-98461a174ffd",
    "valmyndigheten_id": "1301",
    "valmyndigheten_registreringsdatum": "2017-06-27"
  },
  {
    "forkortning": "KVS",
    "name": "kommunens-val",
    "partibeteckning": "Kommunens Väl",
    "uuid": "ed4f86de-92df-4f0c-ae9a-52ccf16de515",
    "valmyndigheten_id": "502",
    "valmyndigheten_registreringsdatum": "2017-12-05"
  },
  {
    "forkortning": "SkuP",
    "name": "skurupspartiet",
    "partibeteckning": "SkurupsPartiet",
    "uuid": "cc204154-12cf-416e-9269-289400cb7334",
    "valmyndigheten_id": "1285",
    "valmyndigheten_registreringsdatum": "2016-06-02"
  },
  {
    "forkortning": "VSKB",
    "name": "vastra-initiativet",
    "partibeteckning": "Västra Initiativet",
    "uuid": "58bd344e-7f53-4c58-97f8-891bbe655d30",
    "valmyndigheten_id": "1002",
    "valmyndigheten_registreringsdatum": "2018-01-15"
  },
  {
    "forkortning": "-",
    "name": "basta-for-sollentuna",
    "partibeteckning": "Bästa för Sollentuna",
    "uuid": "2a220fac-5a89-41fc-87aa-b2572acdb1b8",
    "valmyndigheten_id": "1283",
    "valmyndigheten_registreringsdatum": "2016-05-20"
  },
  {
    "forkortning": "SPA",
    "name": "sollentunapartiet",
    "partibeteckning": "Sollentunapartiet",
    "uuid": "284326c6-e8bd-4864-aa4c-b681444f1490",
    "valmyndigheten_id": "46",
    "valmyndigheten_registreringsdatum": "2018-06-26"
  },
  {
    "forkortning": "BEP",
    "name": "bergshamrapartiet",
    "partibeteckning": "Bergshamrapartiet",
    "uuid": "7c5eb0ea-9c14-4780-a812-358ba6e93674",
    "valmyndigheten_id": "1105",
    "valmyndigheten_registreringsdatum": "2017-12-18"
  },
  {
    "forkortning": "BUSP",
    "name": "bus-partiet",
    "partibeteckning": "BUS-partiet",
    "uuid": "8a7e75a6-a327-4a56-8540-f71fb283ae6f",
    "valmyndigheten_id": "1126",
    "valmyndigheten_registreringsdatum": "2013-11-06"
  },
  {
    "forkortning": "-",
    "name": "solnapartiet",
    "partibeteckning": "Solnapartiet",
    "uuid": "9d142618-dec4-4780-b3a9-9261a5d9c3e1",
    "valmyndigheten_id": "1286",
    "valmyndigheten_registreringsdatum": "2017-10-20"
  },
  {
    "forkortning": "SP",
    "name": "staffanstorpspartiet",
    "partibeteckning": "Staffanstorpspartiet",
    "uuid": "0206e185-1582-43fa-9841-c9f6f7d9653b",
    "valmyndigheten_id": "513",
    "valmyndigheten_registreringsdatum": "2006-01-10"
  },
  {
    "forkortning": "St",
    "name": "stenungsundspartiet",
    "partibeteckning": "Stenungsundspartiet",
    "uuid": "c4592c7f-15b8-4f0b-a0a7-eea1ca935643",
    "valmyndigheten_id": "1323",
    "valmyndigheten_registreringsdatum": "2018-01-16"
  },
  {
    "forkortning": "FS",
    "name": "fria-stockholmare",
    "partibeteckning": "Fria Stockholmare",
    "uuid": "8adf7deb-d476-4bb5-bab8-b6696777d0b9",
    "valmyndigheten_id": "1156",
    "valmyndigheten_registreringsdatum": "2018-03-13"
  },
  {
    "forkortning": "-",
    "name": "solens-frihetsparti",
    "partibeteckning": "Solens Frihetsparti",
    "uuid": "b9432471-caff-4eee-b6a8-35427487a8a6",
    "valmyndigheten_id": "1346",
    "valmyndigheten_registreringsdatum": "2018-03-28"
  },
  {
    "forkortning": "SKL",
    "name": "kommunlistan",
    "partibeteckning": "Kommunlistan",
    "uuid": "9b3fd918-95bb-4366-be5d-27de1a932bc5",
    "valmyndigheten_id": "742",
    "valmyndigheten_registreringsdatum": "2008-02-14"
  },
  {
    "forkortning": "STRP",
    "name": "strangnaspartiet",
    "partibeteckning": "Strängnäspartiet",
    "uuid": "a118a3da-939b-47ec-93c2-1e314818bc7c",
    "valmyndigheten_id": "176",
    "valmyndigheten_registreringsdatum": "1990-01-30"
  },
  {
    "forkortning": "-",
    "name": "jour-stromstad",
    "partibeteckning": "Jour Strömstad",
    "uuid": "ed52f7e6-711c-4a94-ac7c-af60f3e6c5fc",
    "valmyndigheten_id": "1324",
    "valmyndigheten_registreringsdatum": "2017-12-13"
  },
  {
    "forkortning": "rd",
    "name": "rattvis-demokrati",
    "partibeteckning": "Rättvis Demokrati",
    "uuid": "c31b9463-3618-48b3-8a7d-f1c5b46261e6",
    "valmyndigheten_id": "473",
    "valmyndigheten_registreringsdatum": "2005-03-22"
  },
  {
    "forkortning": "SLP",
    "name": "sundbybergs-lokalparti-slp",
    "partibeteckning": "Sundbybergs Lokalparti (SLP)",
    "uuid": "0c5525dc-1f2d-4825-ad75-6f43df31907a",
    "valmyndigheten_id": "1348",
    "valmyndigheten_registreringsdatum": "2018-03-12"
  },
  {
    "forkortning": "GPS",
    "name": "gps-gront-perspektiv-i-sundsvall",
    "partibeteckning": "GPS - Grönt Perspektiv i Sundsvall",
    "uuid": "b12c6352-4b9f-42fb-8743-77114e5496b7",
    "valmyndigheten_id": "1134",
    "valmyndigheten_registreringsdatum": "2014-02-04"
  },
  {
    "forkortning": "SDL",
    "name": "sundsvallspartiet",
    "partibeteckning": "Sundsvallspartiet",
    "uuid": "0651b1bc-cdc5-4bcb-871d-c6f582c3c2bd",
    "valmyndigheten_id": "1165",
    "valmyndigheten_registreringsdatum": "2014-03-13"
  },
  {
    "forkortning": "HS",
    "name": "hela-sunne",
    "partibeteckning": "Hela Sunne",
    "uuid": "407ebcac-23d1-4b6e-b030-d009163bccbe",
    "valmyndigheten_id": "1113",
    "valmyndigheten_registreringsdatum": "2013-06-14"
  },
  {
    "forkortning": "BAP",
    "name": "barapartiet",
    "partibeteckning": "BARAPARTIET",
    "uuid": "1a5522db-9c9a-4c2e-8bc6-a5877671ed18",
    "valmyndigheten_id": "1310",
    "valmyndigheten_registreringsdatum": "2017-10-20"
  },
  {
    "forkortning": "-",
    "name": "fangelsefritt-svedala-partiet",
    "partibeteckning": "Fängelsefritt Svedala Partiet",
    "uuid": "989ba5da-9cbc-4c5e-aaa0-143ab6d0e498",
    "valmyndigheten_id": "1358",
    "valmyndigheten_registreringsdatum": "2018-03-09"
  },
  {
    "forkortning": "ÄS",
    "name": "alska-svedala",
    "partibeteckning": "Älska Svedala",
    "uuid": "ea3d9524-730d-437d-a74e-5b1412f40c7d",
    "valmyndigheten_id": "1379",
    "valmyndigheten_registreringsdatum": "2019-01-11"
  },
  {
    "forkortning": "SOS",
    "name": "sos-stall-om-sverige--soderhamnsinitiativet",
    "partibeteckning": "SOS-Ställ Om Sverige, Söderhamnsinitiativet",
    "uuid": "4b2c8870-d6e5-402a-a4ed-7f68d098869b",
    "valmyndigheten_id": "1360",
    "valmyndigheten_registreringsdatum": "2018-03-09"
  },
  {
    "forkortning": "REAL",
    "name": "realistpartiet",
    "partibeteckning": "Realistpartiet",
    "uuid": "c3388f52-cd86-4212-ad8c-80c7156cc57e",
    "valmyndigheten_id": "1151",
    "valmyndigheten_registreringsdatum": "2018-01-23"
  },
  {
    "forkortning": "TimP",
    "name": "timrapartiet",
    "partibeteckning": "Timråpartiet",
    "uuid": "bd67893c-6cd0-4d19-a06c-f99484952917",
    "valmyndigheten_id": "1322",
    "valmyndigheten_registreringsdatum": "2017-12-05"
  },
  {
    "forkortning": "TIA",
    "name": "tingsrydsalternativet",
    "partibeteckning": "Tingsrydsalternativet",
    "uuid": "11f9b277-29f8-4a27-8894-7adb51cf335c",
    "valmyndigheten_id": "1133",
    "valmyndigheten_registreringsdatum": "2014-01-29"
  },
  {
    "forkortning": "TomP",
    "name": "tomelillapartiet",
    "partibeteckning": "Tomelillapartiet",
    "uuid": "71382aa3-f2e3-4bce-85d5-eda2b31f595a",
    "valmyndigheten_id": "1334",
    "valmyndigheten_registreringsdatum": "2018-01-22"
  },
  {
    "forkortning": "SÖS",
    "name": "soderslattspartiet",
    "partibeteckning": "Söderslättspartiet",
    "uuid": "e7ac6421-62bc-4ef3-aa5b-326acb0811bb",
    "valmyndigheten_id": "1006",
    "valmyndigheten_registreringsdatum": "2010-03-04"
  },
  {
    "forkortning": "ThnF",
    "name": "trollhattans-framtid",
    "partibeteckning": "Trollhättans Framtid",
    "uuid": "30cf6f9d-b1df-4b33-a99d-3cedf3e191b4",
    "valmyndigheten_id": "1278",
    "valmyndigheten_registreringsdatum": "2018-02-26"
  },
  {
    "forkortning": "Ar P",
    "name": "demokratiska-sekulara-socialister-arbetarpartiet",
    "partibeteckning": "Demokratiska Sekulära Socialister Arbetarpartiet",
    "uuid": "59e3d3d7-ca0c-4818-933e-9c6b7e04b1d1",
    "valmyndigheten_id": "1180",
    "valmyndigheten_registreringsdatum": "2019-01-12"
  },
  {
    "forkortning": "VB",
    "name": "vasbys-basta",
    "partibeteckning": "Väsbys Bästa",
    "uuid": "b00bc532-e725-4f3b-9e0a-57ff456e6de1",
    "valmyndigheten_id": "1154",
    "valmyndigheten_registreringsdatum": "2018-01-18"
  },
  {
    "forkortning": "-",
    "name": "uppvidingedemokraterna",
    "partibeteckning": "Uppvidingedemokraterna",
    "uuid": "9017e7c6-3ab7-42fd-9c2a-a25c91807b18",
    "valmyndigheten_id": "1442",
    "valmyndigheten_registreringsdatum": "2019-12-20"
  },
  {
    "forkortning": "Kons",
    "name": "konsensus-for-vadstenas-basta",
    "partibeteckning": "Konsensus - För Vadstenas Bästa",
    "uuid": "35324e37-4fa4-4a29-9370-e75708476d5a",
    "valmyndigheten_id": "1258",
    "valmyndigheten_registreringsdatum": "2018-03-06"
  },
  {
    "forkortning": "NB",
    "name": "nybyggarpartiet",
    "partibeteckning": "Nybyggarpartiet",
    "uuid": "8f5f1ddd-b111-4ae5-a327-4b7d367ca142",
    "valmyndigheten_id": "984",
    "valmyndigheten_registreringsdatum": "2010-02-19"
  },
  {
    "forkortning": "Kp",
    "name": "kommunpartiet-vansbro",
    "partibeteckning": "Kommunpartiet - Vansbro",
    "uuid": "27a67552-e814-43e1-9cbb-c2165d273e4e",
    "valmyndigheten_id": "990",
    "valmyndigheten_registreringsdatum": "2010-02-19"
  },
  {
    "forkortning": "hvkb",
    "name": "hela-vara-kommuns-basta",
    "partibeteckning": "Hela Vara kommuns bästa",
    "uuid": "ae7d2e8b-4cc0-49e9-a27a-109546278c8f",
    "valmyndigheten_id": "1342",
    "valmyndigheten_registreringsdatum": "2018-02-08"
  },
  {
    "forkortning": "WAX",
    "name": "waxholmspartiet-borgerligt-alternativ",
    "partibeteckning": "Waxholmspartiet - borgerligt alternativ",
    "uuid": "60c5adea-ea43-43cf-8ca7-d102a01bcad1",
    "valmyndigheten_id": "1116",
    "valmyndigheten_registreringsdatum": "2013-11-05"
  },
  {
    "forkortning": "VF",
    "name": "vetlanda-framatanda",
    "partibeteckning": "Vetlanda framåtanda",
    "uuid": "91ea834e-a512-48ba-bccc-a7e8bfd1dc75",
    "valmyndigheten_id": "993",
    "valmyndigheten_registreringsdatum": "2010-02-26"
  },
  {
    "forkortning": "PA",
    "name": "politiskt-alternativ",
    "partibeteckning": "Politiskt Alternativ",
    "uuid": "35c4f62f-3e79-4dbe-9ae4-b76aa4052b86",
    "valmyndigheten_id": "983",
    "valmyndigheten_registreringsdatum": "2010-02-19"
  },
  {
    "forkortning": "VTL",
    "name": "vingakerspartiet-vtl",
    "partibeteckning": "Vingåkerspartiet - VTL",
    "uuid": "1ec14dc8-616b-4948-9f91-f739d2f59c78",
    "valmyndigheten_id": "301",
    "valmyndigheten_registreringsdatum": "2018-01-30"
  },
  {
    "forkortning": "VDM",
    "name": "westerwikspartiet",
    "partibeteckning": "Westerwikspartiet",
    "uuid": "b28ca28d-463b-429a-b732-de43333f9096",
    "valmyndigheten_id": "27",
    "valmyndigheten_registreringsdatum": "2015-11-13"
  },
  {
    "forkortning": "-",
    "name": "etableringspartiet",
    "partibeteckning": "EtableringsPartiet",
    "uuid": "7a8f8e52-e026-4d64-b8f8-9147182016f7",
    "valmyndigheten_id": "1271",
    "valmyndigheten_registreringsdatum": "2014-11-25"
  },
  {
    "forkortning": "LibVÅ",
    "name": "liberal-vision-amal",
    "partibeteckning": "Liberal Vision Åmål",
    "uuid": "bd4fff22-4d31-4d12-9abc-adc5fed355ee",
    "valmyndigheten_id": "1353",
    "valmyndigheten_registreringsdatum": "2018-03-06"
  },
  {
    "forkortning": "VFÅ",
    "name": "var-framtids-politiska-utskott",
    "partibeteckning": "Vår Framtids politiska utskott",
    "uuid": "4057e1cb-59cc-4157-b34f-3fac649dc325",
    "valmyndigheten_id": "1166",
    "valmyndigheten_registreringsdatum": "2014-03-13"
  },
  {
    "forkortning": "VV",
    "name": "vastjamtlands-val",
    "partibeteckning": "Västjämtlands Väl",
    "uuid": "c102184c-f0ee-49c9-9250-ab9197f171a1",
    "valmyndigheten_id": "982",
    "valmyndigheten_registreringsdatum": "2018-01-03"
  },
  {
    "forkortning": "N",
    "name": "nordmarkspartiet",
    "partibeteckning": "Nordmarkspartiet",
    "uuid": "896772f7-8ca8-4ee3-9111-3e66278bcf17",
    "valmyndigheten_id": "1072",
    "valmyndigheten_registreringsdatum": "2010-06-18"
  },
  {
    "forkortning": "OPi",
    "name": "opinion",
    "partibeteckning": "Opinion",
    "uuid": "6d796e1b-ae89-46ba-932a-be2bc09a753b",
    "valmyndigheten_id": "1129",
    "valmyndigheten_registreringsdatum": "2014-01-09"
  },
  {
    "forkortning": "ÅSP",
    "name": "aselepartiet",
    "partibeteckning": "Åselepartiet",
    "uuid": "91a0fcf9-1c39-43df-980d-1aa8080054a0",
    "valmyndigheten_id": "185",
    "valmyndigheten_registreringsdatum": "2006-03-07"
  },
  {
    "forkortning": "ÅF",
    "name": "aseles-framtid",
    "partibeteckning": "Åseles framtid",
    "uuid": "c496cc38-e576-4646-bf3f-f8e76d561c56",
    "valmyndigheten_id": "1354",
    "valmyndigheten_registreringsdatum": "2018-03-09"
  },
  {
    "forkortning": "KL",
    "name": "kommunlistan",
    "partibeteckning": "Kommunlistan",
    "uuid": "452aff7e-40d4-44b5-9193-b8e9b006a6da",
    "valmyndigheten_id": "512",
    "valmyndigheten_registreringsdatum": "2006-01-10"
  },
  {
    "forkortning": "KV",
    "name": "kommunens-val",
    "partibeteckning": "Kommunens Väl",
    "uuid": "5f8920c0-71dd-4e2d-8a12-7392ec1d2021",
    "valmyndigheten_id": "40",
    "valmyndigheten_registreringsdatum": "2003-05-14"
  },
  {
    "forkortning": "EP",
    "name": "engelholmspartiet",
    "partibeteckning": "EngelholmsPartiet",
    "uuid": "319daaea-c08a-4e2f-b8a5-c99b5fd9de6c",
    "valmyndigheten_id": "986",
    "valmyndigheten_registreringsdatum": "2010-02-19"
  },
  {
    "forkortning": "ÖHGP",
    "name": "odeshogs-partiet",
    "partibeteckning": "Ödeshögs Partiet",
    "uuid": "a58232ce-38c7-4991-9b96-9179e0d9b4b6",
    "valmyndigheten_id": "1049",
    "valmyndigheten_registreringsdatum": "2014-01-16"
  },
  {
    "forkortning": "ROSP",
    "name": "roslagspartiet",
    "partibeteckning": "Roslagspartiet",
    "uuid": "be71ef20-ecb1-4702-8cdd-98686556b98b",
    "valmyndigheten_id": "465",
    "valmyndigheten_registreringsdatum": "2017-12-08"
  },
  {
    "forkortning": "SPÖ",
    "name": "skolpartiet-i-osteraker",
    "partibeteckning": "Skolpartiet i Österåker",
    "uuid": "06a5f81d-ae11-496f-b222-2145e509d257",
    "valmyndigheten_id": "1145",
    "valmyndigheten_registreringsdatum": "2014-02-25"
  },
  {
    "forkortning": "ÖP",
    "name": "osterakerspartiet",
    "partibeteckning": "Österåkerspartiet",
    "uuid": "2130f9f3-4dbe-4019-9e9d-34e06d9754a1",
    "valmyndigheten_id": "150",
    "valmyndigheten_registreringsdatum": "1994-09-06"
  },
  {
    "forkortning": "BoA",
    "name": "lokalpartiet-boa",
    "partibeteckning": "Lokalpartiet BoA",
    "uuid": "77f0a0cd-c3c5-42ca-86a3-08759e95900d",
    "valmyndigheten_id": "667",
    "valmyndigheten_registreringsdatum": "2017-06-02"
  },
  {
    "forkortning": "MG",
    "name": "mitt-goinge",
    "partibeteckning": "Mitt Göinge",
    "uuid": "db6631d4-61a1-4068-b426-66d75fe39ea1",
    "valmyndigheten_id": "1337",
    "valmyndigheten_registreringsdatum": "2018-02-26"
  },
  {
    "forkortning": "ÖFA",
    "name": "overtorneas-fria-alternativ",
    "partibeteckning": "Övertorneås Fria Alternativ",
    "uuid": "3bd219fb-835a-4d0d-8d26-5f99bdb79381",
    "valmyndigheten_id": "1068",
    "valmyndigheten_registreringsdatum": "2018-03-26"
  }
]
